droneinterface/__init__.py
droneinterface/combinators.py
droneinterface/commands.py
droneinterface/connection.py
droneinterface/last_message.py
droneinterface/vehicle.py
droneinterface-0.0.4.dist-info/LICENSE
droneinterface-0.0.4.dist-info/METADATA
droneinterface-0.0.4.dist-info/WHEEL
droneinterface-0.0.4.dist-info/top_level.txt
droneinterface-0.0.4.dist-info/RECORD
