Metadata-Version: 2.1
Name: droneinterface
Version: 0.0.4
Summary: A tidy way to talk to a Drone through PyMavLink
Home-page: https://github.com/PyFlightCoach/DroneInterface
Author: Thomas David
Author-email: thomasdavid0@gmail.com
License-File: LICENSE
Requires-Dist: pymavlink
Requires-Dist: numpy
Requires-Dist: pandas
Requires-Dist: pfc-geometry >=0.2.5
Requires-Dist: flightdata >=0.2.6
